aias_common/__init__.py
aias_common/logger.py
aias_common/access/__init__.py
aias_common/access/configuration.py
aias_common/access/file.py
aias_common/access/logger.py
aias_common/access/manager.py
aias_common/access/multipart_encoder.py
aias_common/access/storages/__init__.py
aias_common/access/storages/abstract.py
aias_common/access/storages/file.py
aias_common/access/storages/gs.py
aias_common/access/storages/http.py
aias_common/access/storages/https.py
aias_common/access/storages/path_helper.py
aias_common/access/storages/s3.py
aias_common/access/storages/utils.py
aias_common/rest/__init__.py
aias_common/rest/exception.py
aias_common/rest/exception_handler.py
aias_common/rest/healthcheck.py
aias_common/rest/utils.py
aias_common-0.10.6.dist-info/METADATA
aias_common-0.10.6.dist-info/WHEEL
aias_common-0.10.6.dist-info/top_level.txt
aias_common-0.10.6.dist-info/RECORD
