Metadata-Version: 2.1
Name: aias-common
Version: 0.10.6
Summary: ARLAS AIAS common library
Home-page: UNKNOWN
Author: Gisaïa
License: UNKNOWN
Platform: UNKNOWN
Requires-Python: >=3.10
Requires-Dist: ecs-logging
Requires-Dist: google-cloud-storage (==2.5.0)
Requires-Dist: pydantic (==2.10.6)
Requires-Dist: requests (==2.32.4)
Requires-Dist: smart-open (==7.5.0)
Requires-Dist: boto3 (==1.39.11)
Requires-Dist: fastapi-utilities
